.gitignore
LICENCE.txt
README.md
dependencies.txt
setup.cfg
setup.py
src/data_sorter/__init__.py
src/data_sorter/algos/__init__.py
src/data_sorter/algos/brick_sort.py
src/data_sorter/algos/bubble_sort.py
src/data_sorter/algos/bucket_sort.py
src/data_sorter/algos/comb_sort.py
src/data_sorter/algos/counting_sort.py
src/data_sorter/algos/cycle_sort.py
src/data_sorter/algos/gnome_sort.py
src/data_sorter/algos/heap_sort.py
src/data_sorter/algos/insertion_sort.py
src/data_sorter/algos/intro_sort.py
src/data_sorter/algos/merge_sort.py
src/data_sorter/algos/pigeonhole_sort.py
src/data_sorter/algos/quick_sort.py
src/data_sorter/algos/radix_sort.py
src/data_sorter/algos/selection_sort.py
src/data_sorter/algos/stooge_sort.py
src/data_sorter/algos/strand_sort.py
src/data_sorter/algos/tree_sort.py
src/python_sorter.egg-info/PKG-INFO
src/python_sorter.egg-info/SOURCES.txt
src/python_sorter.egg-info/dependency_links.txt
src/python_sorter.egg-info/requires.txt
src/python_sorter.egg-info/top_level.txt