Metadata-Version: 2.1
Name: python-sorter
Version: 1.1.1
Summary: Apply multiple type of sorting algorithm on your data and also compare which sorting is fastes on your data
Home-page: https://github.com/Deep-Dey/python-sorter
Author: Deep Dey
Author-email: deepdey10998@gmail.com
License: MIT
Keywords: sorting python buublesort quicksort mergesort
Platform: UNKNOWN
Classifier: Development Status :: 4 - Beta
Classifier: Intended Audience :: Developers
Classifier: Topic :: Software Development :: Build Tools
Classifier: License :: OSI Approved :: MIT License
Classifier: Programming Language :: Python :: 3
Classifier: Programming Language :: Python :: 3.6
Classifier: Programming Language :: Python :: 3.7
Classifier: Programming Language :: Python :: 3.8
Classifier: Programming Language :: Python :: 3.9
Classifier: Programming Language :: Python :: 3 :: Only
